lico/__init__.py
lico/core.py
lico/exceptions.py
lico/io.py
lico/logging.py
lico/operations.py
lico-0.1.3.dist-info/LICENSE
lico-0.1.3.dist-info/WHEEL
lico-0.1.3.dist-info/METADATA
lico-0.1.3.dist-info/RECORD
