Metadata-Version: 2.1
Name: lico
Version: 0.1.3
Summary: List processing with csv files
License: MIT
Author: sjoerdk
Author-email: sjoerd.kerkstra@radboudumc.nl
Requires-Python: >=3.9,<4.0
Classifier: License :: OSI Approved :: MIT License
Classifier: Programming Language :: Python :: 3
Classifier: Programming Language :: Python :: 3.10
Classifier: Programming Language :: Python :: 3.9
